Classfile /C:/Users/dawid/Desktop/Repos/Java-Bytecode-Interpreter/CheckPrime.class
  Last modified 25 Jul 2025; size 358 bytes
  SHA-256 checksum 17cdcfb45e71978652f750b3b346e30147df4590be4cc6f9172ea910cddb2b9d
  Compiled from "CheckPrime.java"
public class CheckPrime
  minor version: 0
  major version: 68
  flags: (0x0021) ACC_PUBLIC, ACC_SUPER
  this_class: #7                          // CheckPrime
  super_class: #2                         // java/lang/Object
  interfaces: 0, fields: 0, methods: 2, attributes: 1
Constant pool:
   #1 = Methodref          #2.#3          // java/lang/Object."<init>":()V
   #2 = Class              #4             // java/lang/Object
   #3 = NameAndType        #5:#6          // "<init>":()V
   #4 = Utf8               java/lang/Object
   #5 = Utf8               <init>
   #6 = Utf8               ()V
   #7 = Class              #8             // CheckPrime
   #8 = Utf8               CheckPrime
   #9 = Utf8               Code
  #10 = Utf8               LineNumberTable
  #11 = Utf8               main
  #12 = Utf8               ([Ljava/lang/String;)V
  #13 = Utf8               StackMapTable
  #14 = Utf8               SourceFile
  #15 = Utf8               CheckPrime.java
{
  public CheckPrime();
    descriptor: ()V
    flags: (0x0001) ACC_PUBLIC
    Code:
      stack=1, locals=1, args_size=1
         0: aload_0
         1: invokespecial #1                  // Method java/lang/Object."<init>":()V
         4: return
      LineNumberTable:
        line 1: 0

  public static void main(java.lang.String[]);
    descriptor: ([Ljava/lang/String;)V
    flags: (0x0009) ACC_PUBLIC, ACC_STATIC
    Code:
      stack=3, locals=4, args_size=1
         0: bipush        29
         2: istore_1
         3: iconst_0
         4: istore_2
         5: iconst_2
         6: istore_3
         7: iload_3
         8: iload_1
         9: iconst_2
        10: idiv
        11: if_icmpgt     31
        14: iload_1
        15: iload_3
        16: irem
        17: ifne          25
        20: iconst_1
        21: istore_2
        22: goto          31
        25: iinc          3, 1
        28: goto          7
        31: return
      LineNumberTable:
        line 4: 0
        line 5: 3
        line 6: 5
        line 8: 14
        line 9: 20
        line 10: 22
        line 6: 25
        line 13: 31
      StackMapTable: number_of_entries = 3
        frame_type = 254 /* append */
          offset_delta = 7
          locals = [ int, int, int ]
        frame_type = 17 /* same */
        frame_type = 250 /* chop */
          offset_delta = 5
}
SourceFile: "CheckPrime.java"
